[
{
  "name":"com.fasterxml.jackson.databind.JsonDeserializer[]"
},
{
  "name":"com.fasterxml.jackson.databind.JsonSerializer[]"
},
{
  "name":"com.fasterxml.jackson.databind.KeyDeserializer[]"
},
{
  "name":"com.fasterxml.jackson.databind.Module[]"
},
{
  "name":"com.fasterxml.jackson.databind.deser.BeanDeserializerModifier[]"
},
{
  "name":"com.fasterxml.jackson.databind.deser.Deserializers[]"
},
{
  "name":"com.fasterxml.jackson.databind.deser.KeyDeserializers[]"
},
{
  "name":"com.fasterxml.jackson.databind.deser.ValueInstantiators[]"
},
{
  "name":"com.fasterxml.jackson.databind.ext.Java7HandlersImpl",
  "methods":[{"name":"<init>","parameterTypes":[] }]
},
{
  "name":"com.fasterxml.jackson.databind.ext.Java7SupportImpl",
  "methods":[{"name":"<init>","parameterTypes":[] }]
},
{
  "name":"com.fasterxml.jackson.databind.ser.BeanSerializerModifier[]"
},
{
  "name":"com.fasterxml.jackson.databind.ser.Serializers[]"
},
{
  "name":"com.slack.api.model.block.ContextBlockElement",
  "allDeclaredMethods":true
},
{
  "name":"com.slack.api.model.block.DividerBlock",
  "allDeclaredFields":true,
  "allDeclaredMethods":true,
  "allDeclaredConstructors":true
},
{
  "name":"com.slack.api.model.block.LayoutBlock",
  "allDeclaredMethods":true
},
{
  "name":"com.slack.api.model.block.SectionBlock",
  "allDeclaredFields":true,
  "allDeclaredMethods":true,
  "allDeclaredConstructors":true
},
{
  "name":"com.slack.api.model.block.composition.MarkdownTextObject",
  "allDeclaredFields":true,
  "allDeclaredMethods":true,
  "allDeclaredConstructors":true
},
{
  "name":"com.slack.api.model.block.composition.TextObject",
  "allDeclaredFields":true,
  "allDeclaredMethods":true
},
{
  "name":"io.reactivex.Completable"
},
{
  "name":"io.reactivex.Maybe"
},
{
  "name":"io.reactivex.Observable"
},
{
  "name":"io.reactivex.Single"
},
{
  "name":"java.io.Serializable",
  "allDeclaredMethods":true
},
{
  "name":"java.lang.Boolean",
  "allDeclaredFields":true,
  "allDeclaredMethods":true,
  "allDeclaredConstructors":true
},
{
  "name":"java.lang.Comparable",
  "allDeclaredMethods":true
},
{
  "name":"java.lang.String[]"
},
{
  "name":"java.lang.management.ManagementFactory",
  "methods":[{"name":"getRuntimeMXBean","parameterTypes":[] }]
},
{
  "name":"java.lang.management.RuntimeMXBean",
  "methods":[
    {"name":"getInputArguments","parameterTypes":[] }, 
    {"name":"getName","parameterTypes":[] }
  ]
},
{
  "name":"java.lang.reflect.AccessibleObject",
  "fields":[{"name":"override"}]
},
{
  "name":"java.sql.Date"
},
{
  "name":"java.sql.Timestamp"
},
{
  "name":"javax.management.ObjectName"
},
{
  "name":"jdk.internal.misc.Unsafe",
  "methods":[{"name":"getUnsafe","parameterTypes":[] }]
},
{
  "name":"sun.misc.Unsafe",
  "fields":[{"name":"theUnsafe"}],
  "methods":[
    {"name":"copyMemory","parameterTypes":["java.lang.Object","long","java.lang.Object","long","long"] }, 
    {"name":"getAndAddLong","parameterTypes":["java.lang.Object","long","long"] }, 
    {"name":"getAndSetObject","parameterTypes":["java.lang.Object","long","java.lang.Object"] }, 
    {"name":"invokeCleaner","parameterTypes":["java.nio.ByteBuffer"] }
  ]
},
{
  "name":"sun.nio.ch.SelectorImpl",
  "fields":[
    {"name":"publicSelectedKeys", "allowUnsafeAccess":true}, 
    {"name":"selectedKeys", "allowUnsafeAccess":true}
  ]
}
]
